./.gitignore
./Dockerfile
./Dockerfile.full
./PKG-INFO
./README.md
./TOOLS.md
./__init__.py
./a2a.md
./build_and_push.sh
./config.py
./docker-compose.yml
./pyproject.toml
./run_mcp.sh
./server.py
./serverless.yml
./aws/cloudformation.yaml
./aws/deploy.sh
./aws/task-definition.json
./resources/__init__.py
./resources/agent_guide.py
./resources/api_loader.py
./resources/docs_loader.py
./resources/release_notes_loader.py
./tools/__init__.py
./tools/all_tools.py
./tools/global_utils_tools.py
./tools/mcp_tools.py
./tools/sdk_tools.py
./tools/search.py
tf_mcp_server-0.5.8.dist-info/METADATA
tf_mcp_server-0.5.8.dist-info/WHEEL
tf_mcp_server-0.5.8.dist-info/entry_points.txt
tf_mcp_server-0.5.8.dist-info/RECORD
