Metadata-Version: 2.4
Name: tf-mcp-server
Version: 0.5.8
Summary: MCP server for ToothFairyAI documentation
Author-email: ToothFairyAI <support@toothfairyai.com>
License-Expression: MIT
Requires-Python: >=3.10
Requires-Dist: fastmcp>=0.4.0
Requires-Dist: httpx>=0.27.0
Requires-Dist: pydantic>=2.0.0
Requires-Dist: python-frontmatter>=1.0.0
Requires-Dist: toothfairyai>=0.5.5
Requires-Dist: uvicorn>=0.30.0
Provides-Extra: dev
Requires-Dist: pytest-asyncio>=0.23.0; extra == 'dev'
Requires-Dist: pytest>=8.0.0; extra == 'dev'
